odoo/addons/mail_contact_type/README.rst
odoo/addons/mail_contact_type/__init__.py
odoo/addons/mail_contact_type/__manifest__.py
odoo/addons/mail_contact_type/i18n/fr.po
odoo/addons/mail_contact_type/i18n/it.po
odoo/addons/mail_contact_type/i18n/mail_contact_type.pot
odoo/addons/mail_contact_type/models/__init__.py
odoo/addons/mail_contact_type/models/mail_contact_type.py
odoo/addons/mail_contact_type/models/res_partner.py
odoo/addons/mail_contact_type/readme/DESCRIPTION.rst
odoo/addons/mail_contact_type/readme/USAGE.rst
odoo/addons/mail_contact_type/security/ir.model.access.csv
odoo/addons/mail_contact_type/static/description/icon.png
odoo/addons/mail_contact_type/static/description/index.html
odoo/addons/mail_contact_type/tests/__init__.py
odoo/addons/mail_contact_type/tests/test_mail_contact_type.py
odoo/addons/mail_contact_type/views/mail_compose_message_view.xml
odoo/addons/mail_contact_type/views/mail_contact_type.xml
odoo/addons/mail_contact_type/views/menu.xml
odoo/addons/mail_contact_type/views/res_partner.xml
odoo14_addon_mail_contact_type-14.0.1.0.1.dev5.dist-info/METADATA
odoo14_addon_mail_contact_type-14.0.1.0.1.dev5.dist-info/WHEEL
odoo14_addon_mail_contact_type-14.0.1.0.1.dev5.dist-info/top_level.txt
odoo14_addon_mail_contact_type-14.0.1.0.1.dev5.dist-info/RECORD
